unistruct/__init__.py
unistruct/main.py
unistruct/prompts.py
unistruct-2025.12.22083127.dist-info/METADATA
unistruct-2025.12.22083127.dist-info/WHEEL
unistruct-2025.12.22083127.dist-info/top_level.txt
unistruct-2025.12.22083127.dist-info/RECORD
