Metadata-Version: 2.4
Name: unistruct
Version: 2025.12.22083127
Summary: unistruct extracts structured data from unstructured text, aiding project planning and management by converting free-form inputs into actionable details.
Author-email: unistruct <hi@eugene.plus>
License: MIT
Project-URL: Homepage, https://github.com/chigwell/unistruct
Requires-Python: >=3.9
Requires-Dist: langchain-llm7>=0.0.0
Requires-Dist: llmatch-messages>=0.0.0
Requires-Dist: langchain-core>=0.3.0
